{
  "$schema": "https://turbo.build/schema.json",
  "tasks": {
    "build": {
      "dependsOn": ["^build"],
      "inputs": ["$TURBO_DEFAULT$", ".env", ".env.local"],
      "env": [
        "CLERK_FRONTEND_API_URL",
        "CLERK_JWT_ISSUER_DOMAIN",
        "CLERK_SECRET_KEY",
        "CLERK_SKIP_KEY_VALIDATION",
        "CONVEX_DEPLOYMENT",
        "CONVEX_DEPLOY_KEY",
        "FROM_EMAIL",
        "GOOGLE_APPLICATION_CREDENTIALS_JSON",
        "GOOGLE_SHEETS_SHEET_NAME",
        "GOOGLE_SHEETS_SPREADSHEET_ID",
        "NEXT_PUBLIC_CLERK_PUBLISHABLE_KEY",
        "NEXT_PUBLIC_CONVEX_URL",
        "NEXT_PUBLIC_POSTHOG_HOST",
        "NEXT_PUBLIC_POSTHOG_KEY",
        "NEXT_PUBLIC_RAZORPAY_KEY_ID",
        "NEXT_PUBLIC_SITE_URL",
        "NODE_ENV",
        "RAZORPAY_KEY_SECRET",
        "RESEND_API_KEY",
        "SENTRY_AUTH_TOKEN",
        "TO_EMAIL",
        "UPLOADTHING_SECRET",
        "UPLOADTHING_TOKEN",
        "UPSTASH_REDIS_REST_TOKEN",
        "UPSTASH_REDIS_REST_URL",
        "WHATSAPP_API_KEY"
      ],
      "outputs": [".next/**", "!.next/cache/**"]
    },
    "lint": {
      "dependsOn": ["^lint"],
      "inputs": ["$TURBO_DEFAULT$"]
    },
    "type-check": {
      "dependsOn": ["^type-check"],
      "inputs": ["$TURBO_DEFAULT$"]
    }
  }
}
